pjsua2.cpython-38-x86_64-linux-gnu.so
pjsua2_pybind11-0.1a3.dist-info/METADATA
pjsua2_pybind11-0.1a3.dist-info/WHEEL
pjsua2_pybind11-0.1a3.dist-info/top_level.txt
pjsua2_pybind11-0.1a3.dist-info/LICENSE
pjsua2_pybind11-0.1a3.dist-info/RECORD
pjsua2_pybind11.libs/libpj-038f4172.so.2
pjsua2_pybind11.libs/libwebrtc-06ac0ecd.so.2
pjsua2_pybind11.libs/libpjsip-ua-6cd9cb9f.so.2
pjsua2_pybind11.libs/libpjnath-0356da9f.so.2
pjsua2_pybind11.libs/libgsmcodec-8e6f0cce.so.2
pjsua2_pybind11.libs/libpjsua2-5254b6b1.so.2
pjsua2_pybind11.libs/libpjmedia-audiodev-8b614c35.so.2
pjsua2_pybind11.libs/libpjsip-459b242d.so.2
pjsua2_pybind11.libs/libpjmedia-codec-46dee8a1.so.2
pjsua2_pybind11.libs/libsrtp-5b5e97ea.so.2
pjsua2_pybind11.libs/libyuv-622c6f55.so.2
pjsua2_pybind11.libs/libilbccodec-aa2eb38b.so.2
pjsua2_pybind11.libs/libpjmedia-8aa5f361.so.2
pjsua2_pybind11.libs/libpjsip-simple-2a260de2.so.2
pjsua2_pybind11.libs/libpjsua-f5c555a4.so.2
pjsua2_pybind11.libs/libpjmedia-videodev-b38e505b.so.2
pjsua2_pybind11.libs/libresample-720ba908.so.2
pjsua2_pybind11.libs/libspeex-dde7de3b.so.2
pjsua2_pybind11.libs/libg7221codec-550d3bb8.so.2
pjsua2_pybind11.libs/libpjlib-util-de111793.so.2
pjsua2-stubs/__init__.pyi
