Metadata-Version: 2.1
Name: pjsua2-pybind11
Version: 0.1a3
Summary: A Python library wrapped PJSUA2 C++ interface of pjsip/pjproject using pybind11
Author-email: liu xue yan <liu_xue_yan@foxmail.com>
Keywords: sip,rtp,sipua,uac,uas,pj,pjproject,pjsip,pjsua,pjsua2,telephony,telecommunications,communication,phone,softphone
Classifier: License :: OSI Approved :: GNU General Public License v3 or later (GPLv3+)
Classifier: Development Status :: 3 - Alpha
Classifier: Intended Audience :: Developers
Classifier: Intended Audience :: Telecommunications Industry
Classifier: Topic :: Software Development :: Libraries :: Python Modules
Classifier: Topic :: Communications :: Telephony
Classifier: Programming Language :: C++
Requires-Python: >=3.8
License-File: LICENSE
